fuNEGF/models.py
fuNEGF/physical_models.py
fuNEGF-0.1.11.dist-info/LICENSE
fuNEGF-0.1.11.dist-info/METADATA
fuNEGF-0.1.11.dist-info/WHEEL
fuNEGF-0.1.11.dist-info/top_level.txt
fuNEGF-0.1.11.dist-info/RECORD
