Metadata-Version: 2.1
Name: fuNEGF
Version: 0.1.11
Summary: A package for NEGF calculations
Author: L. Vojacek
Author-email: Libor.Vojacek@vutbr.cz
License: BSD 3-Clause License
License-File: LICENSE
Requires-Dist: numpy
Requires-Dist: matplotlib
Requires-Dist: scipy
Requires-Dist: pytest
Requires-Dist: pytest-cov
Requires-Dist: pytest-mpl
